harlequelrah_django/__init__.py
harlequelrah_django/functions.py
harlequelrah_django/validators.py
harlequelrah_django/views.py
harlequelrah_django-0.1.1.dist-info/METADATA
harlequelrah_django-0.1.1.dist-info/WHEEL
harlequelrah_django-0.1.1.dist-info/top_level.txt
harlequelrah_django-0.1.1.dist-info/RECORD
