Metadata-Version: 2.1
Name: harlequelrah_django
Version: 0.1.1
Summary: Package personnalisé pour faciliter  le développement avec python avec django
Home-page: https://github.com/Harlequelrah/My_Python_Library
Author: Harlequelrah
Author-email: maximeatsoudegbovi@example.com
Classifier: Programming Language :: Python :: 3
Classifier: License :: OSI Approved :: GNU Lesser General Public License v3 (LGPLv3)
Classifier: Operating System :: OS Independent
Requires-Python: >=3.10
Requires-Dist: django >=5.1.0
